bankparse/__init__.py
bankparse/utils.py
bankparse/file_manager/__init__.py
bankparse/file_manager/base_statement_file.py
bankparse/file_manager/ca_statement_file.py
bankparse/file_manager/cm_statement_file.py
bankparse/file_manager/utils.py
bankparse/table_manager/__init__.py
bankparse/table_manager/base_table.py
bankparse/table_manager/ca_credit_table.py
bankparse/table_manager/ca_transaction_table.py
bankparse/table_manager/cm_balance_statement_table.py
bankparse/table_manager/cm_credit_table.py
bankparse/table_manager/cm_transaction_table.py
bankparse-0.0.2.dist-info/METADATA
bankparse-0.0.2.dist-info/WHEEL
bankparse-0.0.2.dist-info/licenses/LICENSE
bankparse-0.0.2.dist-info/RECORD
