Metadata-Version: 2.4
Name: bankparse
Version: 0.0.2
Summary: bankparse package
Project-URL: Homepage, https://github.com/bparent11/bankparse
Project-URL: Issues, https://github.com/bparent11/bankparse/issues
Author: bparent11
License-Expression: MIT
License-File: LICENSE
Classifier: Operating System :: OS Independent
Classifier: Programming Language :: Python :: 3
Requires-Python: >=3.11
Requires-Dist: pandas>=2.3.3
Requires-Dist: pdfplumber>=0.11.9
Requires-Dist: typing>=3.10.0.0
Requires-Dist: unidecode>=1.4.0
